pydep/__init__.py
pydep/__main__.py
pydep_cli-0.1.1.dist-info/LICENSE
pydep_cli-0.1.1.dist-info/METADATA
pydep_cli-0.1.1.dist-info/WHEEL
pydep_cli-0.1.1.dist-info/entry_points.txt
pydep_cli-0.1.1.dist-info/top_level.txt
pydep_cli-0.1.1.dist-info/RECORD
