Metadata-Version: 2.1
Name: pydep-cli
Version: 0.1.1
Summary: Create pyproject.toml & poetry.lock dependency files from requirements.txt
Home-page: https://github.com/Devansh3712/PyDep
Author: Devansh Singh
Author-email: devanshamity@gmail.com
License: MIT
Platform: UNKNOWN
Classifier: Programming Language :: Python :: 3
Classifier: License :: OSI Approved :: MIT License
Classifier: Operating System :: OS Independent
Requires-Dist: click (==7.1.2)
